dom/__init__.py
dom/constants.py
dom/exceptions.py
dom/logging_config.py
dom/cli/__init__.py
dom/cli/contest.py
dom/cli/infra.py
dom/cli/init.py
dom/cli/validators.py
dom/core/__init__.py
dom/core/config/__init__.py
dom/core/config/pipeline.py
dom/core/config/loaders/__init__.py
dom/core/config/loaders/contest.py
dom/core/config/loaders/infra.py
dom/core/config/loaders/problem.py
dom/core/config/loaders/team.py
dom/core/operations/__init__.py
dom/core/operations/base.py
dom/core/operations/runner.py
dom/core/operations/contest/__init__.py
dom/core/operations/contest/apply.py
dom/core/operations/contest/load_config.py
dom/core/operations/contest/load_contest_config.py
dom/core/operations/contest/plan_changes.py
dom/core/operations/contest/verify_problemset.py
dom/core/operations/infrastructure/__init__.py
dom/core/operations/infrastructure/apply.py
dom/core/operations/infrastructure/check_status.py
dom/core/operations/infrastructure/destroy.py
dom/core/operations/infrastructure/load_config.py
dom/core/operations/infrastructure/plan_changes.py
dom/core/operations/infrastructure/print_status.py
dom/core/operations/init/__init__.py
dom/core/operations/init/initialize_project.py
dom/core/services/__init__.py
dom/core/services/base.py
dom/core/services/contest/__init__.py
dom/core/services/contest/apply.py
dom/core/services/contest/plan.py
dom/core/services/contest/state.py
dom/core/services/contest/verification.py
dom/core/services/infra/__init__.py
dom/core/services/infra/apply.py
dom/core/services/infra/destroy.py
dom/core/services/infra/plan.py
dom/core/services/infra/rollback.py
dom/core/services/infra/state.py
dom/core/services/infra/status.py
dom/core/services/init/__init__.py
dom/core/services/init/callback.py
dom/core/services/init/contest.py
dom/core/services/init/infra.py
dom/core/services/init/problems.py
dom/core/services/problem/__init__.py
dom/core/services/problem/apply.py
dom/core/services/problem/verify.py
dom/core/services/submission/__init__.py
domjudge_cli-0.4.0.dist-info/METADATA
domjudge_cli-0.4.0.dist-info/WHEEL
domjudge_cli-0.4.0.dist-info/entry_points.txt
domjudge_cli-0.4.0.dist-info/RECORD
