Metadata-Version: 2.4
Name: domjudge-cli
Version: 0.4.0
Summary: CLI tool for managing DOMjudge contests and infrastructure
Project-URL: Homepage, https://github.com/AnasImloul/domjudge-cli
Project-URL: Repository, https://github.com/AnasImloul/domjudge-cli
Project-URL: Issues, https://github.com/AnasImloul/domjudge-cli/issues
Author-email: Anas IMLOUL <anas.imloul27@gmail.com>
License: MIT
Keywords: cli,contest,domjudge,programming
Classifier: Development Status :: 4 - Beta
Classifier: Intended Audience :: Developers
Classifier: License :: OSI Approved :: MIT License
Classifier: Programming Language :: Python :: 3
Classifier: Programming Language :: Python :: 3.10
Classifier: Programming Language :: Python :: 3.11
Classifier: Programming Language :: Python :: 3.12
Classifier: Topic :: Software Development :: Libraries :: Python Modules
Requires-Python: >=3.10
Requires-Dist: bcrypt<6.0,>=4.3.0
Requires-Dist: cryptography<47.0,>=43.0.0
Requires-Dist: jinja2<4.0,>=3.1.6
Requires-Dist: jmespath<2.0,>=1.0.1
Requires-Dist: p2d<1.0,>=0.3.0
Requires-Dist: pydantic<3.0,>=2.11.3
Requires-Dist: pydantic[email]<3.0,>=2.11.3
Requires-Dist: pymysql<2.0,>=1.1.0
Requires-Dist: pyyaml<7.0,>=6.0.2
Requires-Dist: requests<3.0,>=2.32.3
Requires-Dist: rich<15.0,>=13.7.0
Requires-Dist: typeguard<5.0,>=4.4.2
Requires-Dist: typer<0.21,>=0.15.2
Requires-Dist: webcolors<26.0,>=24.11.1
Provides-Extra: dev
Requires-Dist: bandit[toml]<2.0,>=1.7.0; extra == 'dev'
Requires-Dist: black<26.0,>=24.0.0; extra == 'dev'
Requires-Dist: build>=1.0.0; extra == 'dev'
Requires-Dist: import-linter<3.0,>=2.0; extra == 'dev'
Requires-Dist: mypy<2.0,>=1.11.0; extra == 'dev'
Requires-Dist: pre-commit<5.0,>=3.8.0; extra == 'dev'
Requires-Dist: pytest-cov<8.0,>=5.0.0; extra == 'dev'
Requires-Dist: pytest-mock<4.0,>=3.14.0; extra == 'dev'
Requires-Dist: pytest<9.0,>=8.0.0; extra == 'dev'
Requires-Dist: ruff<1.0,>=0.6.0; extra == 'dev'
Requires-Dist: tomli>=2.0.0; (python_version < '3.11') and extra == 'dev'
Requires-Dist: types-pyyaml<7.0,>=6.0.12; extra == 'dev'
Requires-Dist: types-requests<3.0,>=2.32.0; extra == 'dev'
